<!-- Kurila's addition -->
<ModOps>
  <!-- Pool: All Oil Powerplants  -->
  <ModOp Type="addNextSibling" GUID="119"
    Condition="!//Values[Standard/GUID='1500300990']">
    <Asset>
      <Template>ItemEffectTargetPool</Template>
      <Values>
        <Standard>
          <GUID>1500300990</GUID>
          <Name>All Oil Powerplants</Name>
        </Standard>
        <ItemEffectTargetPool>
          <EffectTargetGUIDs>
            <Item>
              <GUID>100780</GUID>
            </Item>
            <Item>
              <GUID>5164</GUID>
            </Item>
          </EffectTargetGUIDs>
        </ItemEffectTargetPool>
      </Values>
    </Asset>
  </ModOp>

  <!-- add to: All Oil Powerplants -->
  <ModOp Type="add" GUID="1500300990"
    Path="/Values/ItemEffectTargetPool/EffectTargetGUIDs">
    <Item>
      <GUID>1500010033</GUID>
    </Item>
    <Item>
      <GUID>1500010459</GUID>
    </Item>
  </ModOp>

  <!-- addjust Items -->
  <ModOp Type="replace" GUID="191373,191377"
    Path="/Values/ItemEffect/EffectTargets">
    <EffectTargets>
      <Item>
        <GUID>193864</GUID>
      </Item>
    </EffectTargets>
  </ModOp>
  <ModOp Type="replace" GUID="191375,191376"
    Path="/Values/ItemEffect/EffectTargets">
    <EffectTargets>
      <Item>
        <GUID>1500300990</GUID>
      </Item>
    </EffectTargets>
  </ModOp>
</ModOps>
