<ModOps>
  <ModOp Type="add" Path="/TextExport/Texts">
    <!-- shared products -->
    <Text>
      <GUID>1500010102</GUID>
      <Text>Käse</Text>
    </Text>
    <Text>
      <GUID>1500010127</GUID>
      <Text>Anzüge</Text>
    </Text>
    <Text>
      <GUID>1500010153</GUID>
      <Text>Werkzeug</Text>
    </Text>
    <Text>
      <GUID>1500010120</GUID>
      <Text>Dosenfisch</Text>
    </Text>
    <Text>
      <GUID>1500010106</GUID>
      <Text>Olivenseife</Text>
    </Text>
    <!-- main -->
    <Text>
      <GUID>601382</GUID>
      <Text>Bauern (Pescatarianer)</Text>
    </Text>
    <Text>
      <GUID>601383</GUID>
      <Text>Arbeiter (Pescatarianer)</Text>
    </Text>
    <Text>
      <GUID>601384</GUID>
      <Text>Handwerker (Pescatarianer)</Text>
    </Text>
    <Text>
      <GUID>1500010100</GUID>
      <Text>Gemeindezentrum</Text>
    </Text>
    <Text>
      <GUID>1500010118</GUID>
      <Text>[AssetData(1500010100) Text]</Text>
    </Text>
    <Text>
      <GUID>1500010119</GUID>
      <Text>[AssetData(1500010100) Text]</Text>
    </Text>
    <Text>
      <GUID>1500010130</GUID>
      <Text>Bauern (Pescatarianer)</Text>
    </Text>
    <Text>
      <GUID>1500010131</GUID>
      <Text>Arbeiter (Pescatarianer)</Text>
    </Text>
    <Text>
      <GUID>1500010132</GUID>
      <Text>Handwerker (Pescatarianer)</Text>
    </Text>
    <Text>
      <GUID>1500010134</GUID>
      <Text>Pescatarianer</Text>
    </Text>
    <Text>
      <GUID>1500010136</GUID>
      <Text>Neue Bevölkerung</Text> <!-- AGE OF -->
    </Text>
    <Text>
      <GUID>1500010137</GUID>
      <Text>Pescatarianer</Text> <!-- AGRICULTURE -->
    </Text>
    <Text>
      <GUID>1500010142</GUID>
      <Text>Pescatarianerhaus</Text>
    </Text>
    <Text>
      <GUID>1500010143</GUID>
      <Text>[AssetData(1500010142) Text]</Text>
    </Text>
    <Text>
      <GUID>1500010144</GUID>
      <Text>[AssetData(1500010142) Text]</Text>
    </Text>
    <Text>
      <GUID>1500010146</GUID>
      <Text>Pescatarianer wohnen hier. Sie stellen die gleichen Arbeitskräfte wie normale Bevölerung, haben aber andere Bedürfnisse.</Text>
    </Text>
    <Text>
      <GUID>1500010147</GUID>
      <Text>Pescatarianer</Text>
    </Text>
    <Text>
      <GUID>1500010148</GUID>
      <Text>Pescatarianer</Text>
    </Text>
    <Text>
      <GUID>1500010186</GUID>
      <Text>[AssetData(1500010134) Text]</Text>
    </Text>
    <Text>
      <GUID>1500010188</GUID>
      <Text>Pescatarianer-Gebäude</Text>
    </Text>
    <Text>
      <GUID>1500010282</GUID>
      <Text>Pescatarianerhäuser</Text>
    </Text>
  </ModOp>
</ModOps>