<ModOps>
  <ModOp Type="add" Path="/TextExport/Texts">
    <Text>
      <GUID>1500010306</GUID>
      <Text>Grüne Dächer</Text>
    </Text>
    <Text>
      <GUID>1500010307</GUID>
      <Text>Aus 'Colored Roofs, Residences'.</Text>
    </Text>
    <Text>
      <GUID>1500010308</GUID>
      <Text>Blaue Dächer</Text>
    </Text>
    <Text>
      <GUID>1500010309</GUID>
      <Text>Bunt mit dunklen Dächern</Text>
    </Text>
    <Text>
      <GUID>1500010310</GUID>
      <Text>Dunkle Dächer</Text>
    </Text>
    <Text>
      <GUID>1500010313</GUID>
      <Text>Bunt mit roten Dächern</Text>
    </Text>
    <Text>
      <GUID>1500010318</GUID>
      <Text>Rote Dächer</Text>
    </Text>
    <Text>
      <GUID>1500010319</GUID>
      <Text>Dunkelrote Dächer</Text>
    </Text>
  </ModOp>
</ModOps>