<ModOps>
  <ModOp Type="add" Path="/TextExport/Texts">
    <Text>
      <GUID>1500010306</GUID>
      <Text>Зелёные крыши</Text>
    </Text>
    <Text>
      <GUID>1500010307</GUID>
      <Text>Из мода "Residence Skins".</Text>
    </Text>
    <Text>
      <GUID>1500010308</GUID>
      <Text>Синие крыши</Text>
    </Text>
    <Text>
      <GUID>1500010309</GUID>
      <Text>Красочный с тёмной крышей</Text>
    </Text>
    <Text>
      <GUID>1500010310</GUID>
      <Text>Тёмные крыши</Text>
    </Text>
    <Text>
      <GUID>1500010313</GUID>
      <Text>Красочный с красной крышей</Text>
    </Text>
    <Text>
      <GUID>1500010318</GUID>
      <Text>Красные крыши</Text>
    </Text>
    <Text>
      <GUID>1500010319</GUID>
      <Text>Тёмно-красные крыши</Text>
    </Text>
    <Text>
      <GUID>1500010322</GUID>
      <Text>Residence Skins (Jakob)</Text> <!-- Mod name -->
    </Text>
    <Text>
      <GUID>1500010199</GUID>
      <Text>Жёлтый кирпич (стиль)</Text> <!-- Yellow Brick Skin -->
    </Text>
    <Text>
      <GUID>1500010834</GUID>
      <Text>Перекрашенный дом.</Text>
    </Text>
    <Text>
      <GUID>1500011103</GUID>
      <Text>Белые стены</Text> <!-- Skin: White Walls -->
    </Text>
  </ModOp>
</ModOps>